dart_vm_client/__init__.py
dart_vm_client/dart_vm_service.proto
dart_vm_client/dart_vm_service_client.py
dart_vm_client/dart_vm_service_manager.py
dart_vm_client/dart_vm_service_pb2.py
dart_vm_client/dart_vm_service_pb2_grpc.py
dart_vm_client/generate_protos.py
dart_vm_client/__pycache__/__init__.cpython-313.pyc
dart_vm_client/__pycache__/dart_vm_service_client.cpython-313.pyc
dart_vm_client/__pycache__/dart_vm_service_manager.cpython-313.pyc
dart_vm_client/__pycache__/dart_vm_service_pb2.cpython-313.pyc
dart_vm_client/__pycache__/dart_vm_service_pb2_grpc.cpython-313.pyc
dart_vm_client/dart_vm_service/.gitignore
dart_vm_client/dart_vm_service/.pubignore
dart_vm_client/dart_vm_service/CHANGELOG.md
dart_vm_client/dart_vm_service/LICENSE
dart_vm_client/dart_vm_service/Makefile
dart_vm_client/dart_vm_service/README.md
dart_vm_client/dart_vm_service/analysis_options.yaml
dart_vm_client/dart_vm_service/pubspec.lock
dart_vm_client/dart_vm_service/pubspec.yaml
dart_vm_client/dart_vm_service/.dart_tool/package_config.json
dart_vm_client/dart_vm_service/.dart_tool/pub/bin/dart_vm_service/dart_vm_service.dart-3.7.2.snapshot
dart_vm_client/dart_vm_service/bin/dart_vm_service.dart
dart_vm_client/dart_vm_service/example/README.md
dart_vm_client/dart_vm_service/example/dart_vm_service_example.dart
dart_vm_client/dart_vm_service/lib/dart_vm_service.dart
dart_vm_client/dart_vm_service/lib/dart_vm_service_grpc_server.dart
dart_vm_client/dart_vm_service/lib/dart_vm_service_library.dart
dart_vm_client/dart_vm_service/lib/dart_vm_service_tool.dart
dart_vm_client/dart_vm_service/lib/flutter_extension_utils.dart
dart_vm_client/dart_vm_service/lib/flutter_finder_extension_utils.dart
dart_vm_client/dart_vm_service/lib/src/grpc_service.dart
dart_vm_client/dart_vm_service/lib/src/generated/dart_vm_service.pb.dart
dart_vm_client/dart_vm_service/lib/src/generated/dart_vm_service.pbenum.dart
dart_vm_client/dart_vm_service/lib/src/generated/dart_vm_service.pbgrpc.dart
dart_vm_client-0.0.1.dev4.dist-info/licenses/LICENSE
dart_vm_client-0.0.1.dev4.dist-info/METADATA
dart_vm_client-0.0.1.dev4.dist-info/WHEEL
dart_vm_client-0.0.1.dev4.dist-info/top_level.txt
dart_vm_client-0.0.1.dev4.dist-info/RECORD
