Metadata-Version: 2.4
Name: dart_vm_client
Version: 0.0.1.dev4
Summary: A Python client library to communicate with a Dart VM Service gRPC server for controlling Flutter applications
Author: Erick Torres-Moreno
License: MIT License
Project-URL: Homepage, https://github.com/ericktorres/dart_vm_client
Project-URL: Bug Tracker, https://github.com/ericktorres/dart_vm_client/issues
Classifier: Programming Language :: Python :: 3
Classifier: License :: OSI Approved :: MIT License
Classifier: Operating System :: OS Independent
Requires-Python: >=3.9
License-File: LICENSE
Requires-Dist: grpcio<1.72.0,>=1.71.0
Requires-Dist: protobuf<6.0dev0,>=5.26.1
Requires-Dist: grpcio-tools<1.72.0,>=1.71.0
Dynamic: license-file
